chaosdb/grafana.py
chaosdb/influx.py
chaosdb/litedb.py
chaosdb/utils.py
scripts/test.py
scripts/update_version_major.py
scripts/update_version_minor.py
tests/test_grafana_control.py
tests/test_influx_control.py
tests/test_influx_encoding.py
tests/test_sqlite_control.py
chaosdb-0.2.12.dist-info/LICENSE
chaosdb-0.2.12.dist-info/METADATA
chaosdb-0.2.12.dist-info/WHEEL
chaosdb-0.2.12.dist-info/top_level.txt
chaosdb-0.2.12.dist-info/RECORD
