Metadata-Version: 2.1
Name: chaosdb
Version: 0.2.12
Summary: A Chaostoolkit control to store events on a time series datastore or Grafana
Home-page: https://github.com/sky-uk/chaostoolkit-storeevent
Author: Marco Masetti
Author-email: marco.masetti@sky.uk
License: Revised BSD License
Keywords: chaostoolkit,control,events
Platform: UNKNOWN
Classifier: Development Status :: 2 - Pre-Alpha
Classifier: Intended Audience :: Developers
Classifier: License :: OSI Approved :: BSD License
Classifier: Natural Language :: English
Classifier: Programming Language :: Python :: 3
Classifier: Programming Language :: Python :: 3.7
Classifier: Programming Language :: Python :: 3.8
Classifier: Programming Language :: Python :: 3.9
Requires-Python: >=3.6
